command/cli.py
sycommon/__init__.py
sycommon/services.py
sycommon/config/Config.py
sycommon/config/DatabaseConfig.py
sycommon/config/EmbeddingConfig.py
sycommon/config/LLMConfig.py
sycommon/config/LangfuseConfig.py
sycommon/config/MQConfig.py
sycommon/config/RerankerConfig.py
sycommon/config/SentryConfig.py
sycommon/config/__init__.py
sycommon/database/async_base_db_service.py
sycommon/database/async_database_service.py
sycommon/database/base_db_service.py
sycommon/database/database_service.py
sycommon/health/__init__.py
sycommon/health/health_check.py
sycommon/health/metrics.py
sycommon/health/ping.py
sycommon/llm/__init__.py
sycommon/llm/embedding.py
sycommon/llm/get_llm.py
sycommon/llm/llm_logger.py
sycommon/llm/llm_tokens.py
sycommon/llm/struct_token.py
sycommon/llm/sy_langfuse.py
sycommon/llm/usage_token.py
sycommon/logging/__init__.py
sycommon/logging/async_sql_logger.py
sycommon/logging/kafka_log.py
sycommon/logging/logger_levels.py
sycommon/logging/logger_wrapper.py
sycommon/logging/sql_logger.py
sycommon/middleware/__init__.py
sycommon/middleware/context.py
sycommon/middleware/cors.py
sycommon/middleware/docs.py
sycommon/middleware/exception.py
sycommon/middleware/middleware.py
sycommon/middleware/monitor_memory.py
sycommon/middleware/mq.py
sycommon/middleware/timeout.py
sycommon/middleware/traceid.py
sycommon/models/__init__.py
sycommon/models/base_http.py
sycommon/models/log.py
sycommon/models/mqlistener_config.py
sycommon/models/mqmsg_model.py
sycommon/models/mqsend_config.py
sycommon/models/sso_user.py
sycommon/notice/__init__.py
sycommon/notice/uvicorn_monitor.py
sycommon/rabbitmq/rabbitmq_client.py
sycommon/rabbitmq/rabbitmq_pool.py
sycommon/rabbitmq/rabbitmq_service.py
sycommon/rabbitmq/rabbitmq_service_client_manager.py
sycommon/rabbitmq/rabbitmq_service_connection_monitor.py
sycommon/rabbitmq/rabbitmq_service_consumer_manager.py
sycommon/rabbitmq/rabbitmq_service_core.py
sycommon/rabbitmq/rabbitmq_service_producer_manager.py
sycommon_python_lib-0.1.59.dist-info/METADATA
sycommon_python_lib-0.1.59.dist-info/WHEEL
sycommon_python_lib-0.1.59.dist-info/entry_points.txt
sycommon_python_lib-0.1.59.dist-info/top_level.txt
sycommon_python_lib-0.1.59.dist-info/RECORD
