Metadata-Version: 2.4
Name: sycommon-python-lib
Version: 0.1.59
Summary: Add your description here
Requires-Python: >=3.11
Requires-Dist: aio-pika>=9.5.8
Requires-Dist: aiohttp>=3.13.3
Requires-Dist: aiomysql>=0.3.2
Requires-Dist: decorator>=5.2.1
Requires-Dist: fastapi>=0.128.0
Requires-Dist: kafka-python>=2.3.0
Requires-Dist: langchain>=1.2.3
Requires-Dist: langchain-core>=1.2.7
Requires-Dist: langchain-openai>=1.1.7
Requires-Dist: langfuse>=3.11.2
Requires-Dist: langgraph>=1.0.6
Requires-Dist: loguru>=0.7.3
Requires-Dist: mysql-connector-python>=9.5.0
Requires-Dist: nacos-sdk-python<3.0,>=2.0.9
Requires-Dist: psutil>=7.2.1
Requires-Dist: pydantic>=2.12.5
Requires-Dist: python-dotenv>=1.2.1
Requires-Dist: pyyaml>=6.0.3
Requires-Dist: sentry-sdk[fastapi]>=2.49.0
Requires-Dist: sqlalchemy[asyncio]>=2.0.45
Requires-Dist: starlette>=0.50.0
Requires-Dist: tiktoken>=0.12.0
Requires-Dist: uvicorn>=0.40.0
